aioworkers_pg/__init__.py
aioworkers_pg/base.py
aioworkers_pg/formatter.py
aioworkers_pg/sa.py
aioworkers_pg/sql.py
aioworkers_pg/storage.py
aioworkers_pg-0.3.0.dist-info/LICENSE
aioworkers_pg-0.3.0.dist-info/WHEEL
aioworkers_pg-0.3.0.dist-info/METADATA
aioworkers_pg-0.3.0.dist-info/RECORD
