Metadata-Version: 2.1
Name: aioworkers-pg
Version: 0.3.0
Summary: Module for working with PostgreSQL via asyncpg
Home-page: https://github.com/aioworkers/aioworkers-pg
License: Apache Software License 2.0
Author: Alexander Bogushov
Author-email: abogushov@gmail.com
Requires-Python: >=3.6,<4.0
Classifier: Development Status :: 2 - Pre-Alpha
Classifier: Intended Audience :: Developers
Classifier: License :: OSI Approved :: Apache Software License
Classifier: License :: Other/Proprietary License
Classifier: Programming Language :: Python :: 3
Classifier: Programming Language :: Python :: 3.10
Classifier: Programming Language :: Python :: 3.6
Classifier: Programming Language :: Python :: 3.7
Classifier: Programming Language :: Python :: 3.8
Classifier: Programming Language :: Python :: 3.9
Provides-Extra: sa
Requires-Dist: aioworkers (>=0.15)
Requires-Dist: asyncpg (>=0.22.0)
Project-URL: Repository, https://github.com/aioworkers/aioworkers-pg
